collinsdict/__init__.py
collinsdict/db.py
collinsdict/utils.py
collinsdict/word.py
collinsdict-0.1.0.dist-info/LICENSE
collinsdict-0.1.0.dist-info/METADATA
collinsdict-0.1.0.dist-info/WHEEL
collinsdict-0.1.0.dist-info/top_level.txt
collinsdict-0.1.0.dist-info/RECORD
