Metadata-Version: 2.1
Name: collinsdict
Version: 0.1.0
Summary: Collins Dictionary
Home-page: https://github.com/Lisz21/CollinsDict
Author: liszt21
Author-email: 1832666492@qq.com
License: UNKNOWN
Platform: UNKNOWN
